.gitignore
COPYING
README.txt
requirements.txt
setup.py
ebdata/__init__.py
ebdata.egg-info/PKG-INFO
ebdata.egg-info/SOURCES.txt
ebdata.egg-info/dependency_links.txt
ebdata.egg-info/entry_points.txt
ebdata.egg-info/requires.txt
ebdata.egg-info/top_level.txt
ebdata/blobs/__init__.py
ebdata/blobs/auto_purge.py
ebdata/blobs/create_seeds.py
ebdata/blobs/geotagging.py
ebdata/blobs/manual.py
ebdata/blobs/models.py
ebdata/blobs/scrapers.py
ebdata/blobs/update_feeds.py
ebdata/blobs/migrations/0001_initial.py
ebdata/blobs/migrations/__init__.py
ebdata/geotagger/__init__.py
ebdata/geotagger/models.py
ebdata/geotagger/tests.py
ebdata/geotagger/urls.py
ebdata/geotagger/views.py
ebdata/nlp/__init__.py
ebdata/nlp/addresses.py
ebdata/nlp/datelines.py
ebdata/nlp/models.py
ebdata/nlp/places.py
ebdata/nlp/tests/__init__.py
ebdata/nlp/tests/test_datelines.py
ebdata/nlp/tests/tests.py
ebdata/parsing/__init__.py
ebdata/parsing/dbf.py
ebdata/parsing/excel.py
ebdata/parsing/mdb.py
ebdata/parsing/pdftotext.py
ebdata/parsing/unicodecsv.py
ebdata/retrieval/__init__.py
ebdata/retrieval/log.py
ebdata/retrieval/log_debug.py
ebdata/retrieval/models.py
ebdata/retrieval/retrievers.py
ebdata/retrieval/utils.py
ebdata/retrieval/scrapers/__init__.py
ebdata/retrieval/scrapers/base.py
ebdata/retrieval/scrapers/list_detail.py
ebdata/retrieval/scrapers/newsitem_list_detail.py
ebdata/retrieval/scrapers/tests.py
ebdata/retrieval/scrapers/fixtures/test_scraper_fixtures.json
ebdata/retrieval/updaterdaemon/__init__.py
ebdata/retrieval/updaterdaemon/config.py
ebdata/retrieval/updaterdaemon/initscript
ebdata/retrieval/updaterdaemon/runner.py
ebdata/scrapers/__init__.py
ebdata/scrapers/general/__init__.py
ebdata/scrapers/general/flickr/__init__.py
ebdata/scrapers/general/flickr/flickr_retrieval.py
ebdata/scrapers/general/flickr/photos_schema.json
ebdata/scrapers/general/georss/__init__.py
ebdata/scrapers/general/georss/local_news_schema.json
ebdata/scrapers/general/georss/retrieval.py
ebdata/scrapers/general/meetup/__init__.py
ebdata/scrapers/general/meetup/meetup_retrieval.py
ebdata/scrapers/general/meetup/meetup_schema.json
ebdata/scrapers/general/open311/__init__.py
